<?xml version="1.0" encoding="UTF-8"?>
<persistence version="2.1" xmlns="http://xmlns.jcp.org/xml/ns/persistence" xmlns:xsi="http://www.w3.org/2001/XMLSchema-instance" xsi:schemaLocation="http://xmlns.jcp.org/xml/ns/persistence http://xmlns.jcp.org/xml/ns/persistence/persistence_2_1.xsd">
  <persistence-unit name="DATA_SOURCE" transaction-type="RESOURCE_LOCAL">
    <provider>org.eclipse.persistence.jpa.PersistenceProvider</provider>
    <class>com.jobits.pos.domain.models.TransaccionSalida</class>
    <class>com.jobits.pos.domain.models.Almacen</class>
    <class>com.jobits.pos.domain.models.ProductoVenta</class>
    <class>com.jobits.pos.domain.models.NotificacionEnvioCocina</class>
    <class>com.jobits.pos.domain.models.Pago</class>
    <class>com.jobits.pos.domain.models.ProductovOrden</class>
    <class>com.jobits.pos.domain.models.Carta</class>
    <class>com.jobits.pos.domain.models.Factura</class>
    <class>com.jobits.pos.domain.models.DatosPersonales</class>
    <class>com.jobits.pos.domain.models.Gasto</class>
    <class>com.jobits.pos.domain.models.Area</class>
    <class>com.jobits.pos.domain.models.ActivoFijo</class>
    <class>com.jobits.pos.domain.models.ProductoInsumo</class>
    <class>com.jobits.pos.domain.models.TransaccionMerma</class>
    <class>com.jobits.pos.domain.models.Nota</class>
    <class>com.jobits.pos.domain.models.Impresora</class>
    <class>com.jobits.pos.domain.models.Configuracion</class>
    <class>com.jobits.pos.domain.models.Extraccion</class>
    <class>com.jobits.pos.domain.models.PuestoTrabajo</class>
    <class>com.jobits.pos.domain.models.Log</class>
    <class>com.jobits.pos.domain.models.Seccion</class>
    <class>com.jobits.pos.domain.models.Mesa</class>
    <class>com.jobits.pos.domain.models.IpvVentaRegistro</class>
    <class>com.jobits.pos.domain.models.InsumoAlmacen</class>
    <class>com.jobits.pos.domain.models.ContabilidadCuenta</class>
    <class>com.jobits.pos.domain.models.TransaccionTransformacion</class>
    <class>com.jobits.pos.domain.models.Proveedor</class>
    <class>com.jobits.pos.domain.models.Orden</class>
    <class>com.jobits.pos.domain.models.AsistenciaPersonal</class>
    <class>com.jobits.pos.domain.models.Operacion</class>
    <class>com.jobits.pos.domain.models.Ubicacion</class>
    <class>com.jobits.pos.domain.models.Cocina</class>
    <class>com.jobits.pos.domain.models.Insumo</class>
    <class>com.jobits.pos.domain.models.Negocio</class>
    <class>com.jobits.pos.domain.models.Ipv</class>
    <class>com.jobits.pos.domain.models.TransaccionEntrada</class>
    <class>com.jobits.pos.domain.models.Venta</class>
    <class>com.jobits.pos.domain.models.Personal</class>
    <class>com.jobits.pos.domain.models.IpvRegistro</class>
    <class>com.jobits.pos.domain.models.InsumoElaborado</class>
    <class>com.jobits.pos.domain.models.TipoGasto</class>
    <class>com.jobits.pos.domain.models.Cliente</class>
    <class>com.jobits.pos.domain.models.Transaccion</class>
    <class>com.jobits.pos.domain.models.TransaccionTraspaso</class>
    <class>com.jobits.pos.domain.models.GastoVenta</class>
  </persistence-unit>
</persistence>
